Pokemon/__init__.py
Pokemon/funciones.py
pfcpa_pokemon_pjzd-1.0.0.dist-info/licenses/LICENSE.txt
pfcpa_pokemon_pjzd-1.0.0.dist-info/METADATA
pfcpa_pokemon_pjzd-1.0.0.dist-info/WHEEL
pfcpa_pokemon_pjzd-1.0.0.dist-info/top_level.txt
pfcpa_pokemon_pjzd-1.0.0.dist-info/RECORD
