Metadata-Version: 2.4
Name: PFCPA_Pokemon_PJZD
Version: 1.0.0
Summary: Librería para consultar estadísticas de Pokémon por grupo a partir de un CSV.
Author: Pedro Javier Zambudio Decillis
Author-email: pjzambudio@gmail.com
License: MIT
Keywords: curso,pokemon,consultas,stats
Classifier: Development Status :: 3 - Alpha
Classifier: Intended Audience :: Developers
Classifier: Topic :: Software Development :: Build Tools
Classifier: License :: OSI Approved :: MIT License
Classifier: Programming Language :: Python :: 3
Classifier: Programming Language :: Python :: 3.8
Classifier: Programming Language :: Python :: 3.9
Classifier: Programming Language :: Python :: 3.10
Requires-Python: >=3.8
License-File: LICENSE.txt
Requires-Dist: pandas==2.3.3
Requires-Dist: aiohttp==3.13.2
Dynamic: author
Dynamic: author-email
Dynamic: classifier
Dynamic: description
Dynamic: description-content-type
Dynamic: keywords
Dynamic: license
Dynamic: license-file
Dynamic: requires-dist
Dynamic: requires-python
Dynamic: summary
